{
    "Ar36": {
        "error": 1.6747192375412772e-07,
        "error_type": "SEM",
        "filter_outliers_dict": {
            "filter_outliers": true,
            "iterations": 1,
            "std_devs": 2
        },
        "fit": "linear",
        "value": 0.00018873456423014408
    },
    "Ar37": {
        "error": 2.962941332298572e-07,
        "error_type": "SEM",
        "filter_outliers_dict": {
            "filter_outliers": true,
            "iterations": 1,
            "std_devs": 2
        },
        "fit": "linear",
        "value": -1.108316258949346e-05
    },
    "Ar38": {
        "error": 3.2320119784680857e-07,
        "error_type": "SEM",
        "filter_outliers_dict": {
            "filter_outliers": true,
            "iterations": 1,
            "std_devs": 2
        },
        "fit": "linear",
        "value": -0.00014740319360859988
    },
    "Ar39": {
        "error": 5.145802511007213e-07,
        "error_type": "SEM",
        "filter_outliers_dict": {
            "filter_outliers": true,
            "iterations": 1,
            "std_devs": 2
        },
        "fit": "linear",
        "value": -7.881835749182953e-06
    },
    "Ar40": {
        "error": 2.4691821128413424e-05,
        "error_type": "SEM",
        "filter_outliers_dict": {
            "filter_outliers": true,
            "iterations": 1,
            "std_devs": 2
        },
        "fit": "parabolic",
        "value": 0.07306626541157486
    }
}